parsgod/__init__.py
parsgod/parsgod.py
parsgod-0.0.11.dist-info/LICENSE
parsgod-0.0.11.dist-info/METADATA
parsgod-0.0.11.dist-info/WHEEL
parsgod-0.0.11.dist-info/top_level.txt
parsgod-0.0.11.dist-info/RECORD
