Metadata-Version: 2.1
Name: parsgod
Version: 0.0.11
Summary: A module for generating the python parser framework
Author: Alexander554
Author-email: gaa.280811@gmail.com
License: MIT
License-File: LICENSE
Requires-Dist: requests
